{
  "u-region-select/data": {
    "type": "Array<{ text, value }>",
    "description": "数据列表"
  },
  "u-region-select/value": {
    "type": "any",
    "description": "当前选择的值"
  },
  "u-region-select/categories": {
    "type": "Array<{ label, key, placeholder }>",
    "description": "多级分类"
  },
  "u-region-select/hide-empty": {
    "type": "boolean",
    "description": "是否隐藏空列表"
  },
  "u-region-select/converter": {
    "type": "string, object",
    "description": "value 与 values 的转换器。可选值：`'join'`表示将 values 数组 join 之后变成 value，`'join.number'`与`join`类似，只是会考虑它为数字的情况。也可以用`:`修改分隔符，类似 Vue 的指令参数，`'last-value'`表示以最后一项的值作为 value。也可以传入一个包含 { get, set } 的一个对象"
  },
  "u-region-select/field": {
    "type": "string",
    "description": "显示文本字段"
  },
  "u-region-select/readonly": {
    "type": "boolean",
    "description": "是否只读"
  },
  "u-region-select/disabled": {
    "type": "boolean",
    "description": "是否禁用"
  }
}