{
  "lcap-printPage/hidden": {
    "type": "boolean",
    "description": "是否显示打印按钮"
  },
  "lcap-printPage/fileName": {
    "type": "string",
    "description": "设置打印的文件名称"
  },
  "lcap-printPage/printDOM": {
    "type": "string",
    "description": "设置打印的DOM节点"
  },
  "lcap-printPage/canvasWidth": {
    "type": "number",
    "description": "设置打印文件的宽度"
  },
  "lcap-printPage/canvasHeight": {
    "type": "number",
    "description": "设置打印文件的高度"
  },
  "lcap-printPage/download": {
    "type": "boolean",
    "description": "是否自动下载打印的文件"
  },
  "lcap-printPage/fileType": {
    "type": "string",
    "options": [
      {
        "value": "pdf",
        "title": "PDF"
      },
      {
        "value": "png",
        "title": "PNG"
      }
    ],
    "description": "设置打印的文件类型"
  }
}